{
  "posts": [
    {
     "id": 1,
    "name": "Leanne Graham",
    "lastname": "Bret",
    "email": "Sincere@april.biz",
    "gender": "female",
     "skillset": "plumber",
    "address": {
      "street": "Kulas Light",
      "suite": "Apt. 556",
      "city": "Gwenborough",
      "zipcode": "92998-3874",
      "geo": {
        "lat": "-37.3159",
        "lng": "81.1496"
      }
    },
    "phone": "1-770-736-8031 x56442",
    "website": "hildegard.org",
    "company": {
      "name": "Romaguera-Crona",
      "catchPhrase": "Multi-layered client-server neural-net",
      "bs": "harness real-time e-markets"
    }
    },
    {
      "id": 2,
      "name": "Graham",
      "lastname": "Bill",
      "email": "Sincere1qw@april.biz",
      "gender": "female",
      "skillset": "nanny",
      "address": {
        "street": "Kulas Lightqww",
        "suite": "Apt. 55612",
        "city": "Gwenboroughs",
        "zipcode": "92998-38742",
        "geo": {
          "lat": "-37.31591",
          "lng": "81.14962"
        }
      },
      "phone": "1-770-736-8031 x56432",
      "website": "hildegard.org",
      "company": {
        "name": "Romaguera-Crona",
        "catchPhrase": "Multi-layered client-server neural-net",
        "bs": "harness real-time e-markets"
      }
    },
    {
      "id": 3,
      "name": "Graham",
      "lastname": "Billy",
      "email": "Sincere1qw23@april.biz",
      "gender": "female",
      "skillset": "panday",
      "address": {
        "street": "Kulas Lightshow",
        "suite": "Apt. 55622",
        "city": "Gwensboroughs",
        "zipcode": "92998-33742",
        "geo": {
          "lat": "-37.31591",
          "lng": "81.14962"
        }
      },
      "phone": "2-770-736-8031 x56432",
      "website": "hildegard.org",
      "company": {
        "name": "Romaguera-Crona",
        "catchPhrase": "Multi-layered client-server neural-net",
        "bs": "harness real-time e-markets"
      }
    }
  ],
  
}
